frequenz/data/py.typed
frequenz/data/microgrid/__init__.py
frequenz/data/microgrid/_stateful_data_fetcher.py
frequenz/data/microgrid/component_data.py
frequenz/datasci/__init__.py
frequenz/datasci/weather/__init__.py
frequenz/datasci/weather/py.typed
frequenz/datasci/weather/weather_api.py
frequenz/lib/notebooks/__init__.py
frequenz/lib/notebooks/config.py
frequenz/lib/notebooks/conftest.py
frequenz/lib/notebooks/notification_service.py
frequenz/lib/notebooks/notification_utils.py
frequenz/lib/notebooks/py.typed
frequenz/lib/notebooks/alerts/__init__.py
frequenz/lib/notebooks/alerts/alert_email.py
frequenz/lib/notebooks/reporting/__init__.py
frequenz/lib/notebooks/reporting/_state_records.py
frequenz/lib/notebooks/reporting/data_processing.py
frequenz/lib/notebooks/reporting/plotter.py
frequenz/lib/notebooks/reporting/schema_mapping.yaml
frequenz/lib/notebooks/reporting/state_analysis.py
frequenz/lib/notebooks/reporting/asset_optimization/__init__.py
frequenz/lib/notebooks/reporting/asset_optimization/data.py
frequenz/lib/notebooks/reporting/asset_optimization/viz_mpl.py
frequenz/lib/notebooks/reporting/metrics/__init__.py
frequenz/lib/notebooks/reporting/metrics/reporting_metrics.py
frequenz/lib/notebooks/reporting/utils/__init__.py
frequenz/lib/notebooks/reporting/utils/column_mapper.py
frequenz/lib/notebooks/reporting/utils/helpers.py
frequenz/lib/notebooks/reporting/utils/reporting_nb_functions.py
frequenz/lib/notebooks/solar/__init__.py
frequenz/lib/notebooks/solar/maintenance/__init__.py
frequenz/lib/notebooks/solar/maintenance/config.py
frequenz/lib/notebooks/solar/maintenance/dashboard_styles.py
frequenz/lib/notebooks/solar/maintenance/dashboard_templates.py
frequenz/lib/notebooks/solar/maintenance/data_fetch.py
frequenz/lib/notebooks/solar/maintenance/data_processing.py
frequenz/lib/notebooks/solar/maintenance/microgrid_dashboard.py
frequenz/lib/notebooks/solar/maintenance/models.py
frequenz/lib/notebooks/solar/maintenance/plot_manager.py
frequenz_lib_notebooks-0.14.3.dist-info/licenses/LICENSE
frequenz_lib_notebooks-0.14.3.dist-info/licenses/LICENSE.txt
frequenz_lib_notebooks-0.14.3.dist-info/METADATA
frequenz_lib_notebooks-0.14.3.dist-info/WHEEL
frequenz_lib_notebooks-0.14.3.dist-info/top_level.txt
frequenz_lib_notebooks-0.14.3.dist-info/RECORD
