Metadata-Version: 2.4
Name: frequenz-lib-notebooks
Version: 0.14.3
Summary: Tooling for notebooks.
Author-email: Frequenz Energy-as-a-Service GmbH <floss@frequenz.com>
License: MIT
Project-URL: Documentation, https://frequenz-floss.github.io/frequenz-lib-notebooks/
Project-URL: Changelog, https://github.com/frequenz-floss/frequenz-lib-notebooks/releases
Project-URL: Issues, https://github.com/frequenz-floss/frequenz-lib-notebooks/issues
Project-URL: Repository, https://github.com/frequenz-floss/frequenz-lib-notebooks
Project-URL: Support, https://github.com/frequenz-floss/frequenz-lib-notebooks/discussions/categories/support
Keywords: frequenz,python,lib,library,frequenz-lib-notebooks,tooling,notebooks
Classifier: Development Status :: 3 - Alpha
Classifier: Intended Audience :: Developers
Classifier: License :: OSI Approved :: MIT License
Classifier: Programming Language :: Python :: 3
Classifier: Programming Language :: Python :: 3 :: Only
Classifier: Topic :: Software Development :: Libraries
Classifier: Typing :: Typed
Requires-Python: <4,>=3.11
License-File: LICENSE
License-File: LICENSE.txt
Requires-Dist: typing-extensions<5,>=4.14.1
Requires-Dist: numpy<3,>=2.3.1
Requires-Dist: pandas<3,>=2.3.1
Requires-Dist: pyarrow<23.0.0,>=20.0.0
Requires-Dist: matplotlib<3.11.0,>=3.9.2
Requires-Dist: ipython==9.8.0
Requires-Dist: pvlib<0.14.0,>=0.13.0
Requires-Dist: python-dotenv<1.3.0,>=0.21.0
Requires-Dist: toml<0.11.0,>=0.10.2
Requires-Dist: marshmallow-dataclass<9,>=8.7.1
Requires-Dist: plotly<6.6.0,>=6.0.0
Requires-Dist: kaleido<1.3.0,>=0.2.1
Requires-Dist: frequenz-client-reporting<0.21.0,>=0.20.0
Requires-Dist: frequenz-client-weather<0.3.0,>=0.2.3
Requires-Dist: frequenz-gridpool<0.4,>=0.1.1
Requires-Dist: types-pyyaml>=6.0.12.20250915
Requires-Dist: marshmallow<5,>=4.1.0
Requires-Dist: pyyaml>=6.0.3
Requires-Dist: pytz>=2025.2
Provides-Extra: dev-flake8
Requires-Dist: flake8==7.3.0; extra == "dev-flake8"
Requires-Dist: flake8-docstrings==1.7.0; extra == "dev-flake8"
Requires-Dist: flake8-pyproject==1.2.4; extra == "dev-flake8"
Requires-Dist: pydoclint==0.8.3; extra == "dev-flake8"
Requires-Dist: pydocstyle==6.3.0; extra == "dev-flake8"
Provides-Extra: dev-formatting
Requires-Dist: black==25.12.0; extra == "dev-formatting"
Requires-Dist: isort==7.0.0; extra == "dev-formatting"
Provides-Extra: dev-mkdocs
Requires-Dist: Markdown==3.10; extra == "dev-mkdocs"
Requires-Dist: black==25.12.0; extra == "dev-mkdocs"
Requires-Dist: mike==2.1.3; extra == "dev-mkdocs"
Requires-Dist: mkdocs-gen-files==0.6.0; extra == "dev-mkdocs"
Requires-Dist: mkdocs-literate-nav==0.6.2; extra == "dev-mkdocs"
Requires-Dist: mkdocs-macros-plugin==1.5.0; extra == "dev-mkdocs"
Requires-Dist: mkdocs-material==9.7.1; extra == "dev-mkdocs"
Requires-Dist: mkdocstrings[python]==1.0.0; extra == "dev-mkdocs"
Requires-Dist: mkdocstrings-python==1.18.2; extra == "dev-mkdocs"
Requires-Dist: frequenz-repo-config[lib]==0.13.8; extra == "dev-mkdocs"
Provides-Extra: dev-mypy
Requires-Dist: mypy==1.19.1; extra == "dev-mypy"
Requires-Dist: pandas-stubs==2.3.3.251219; extra == "dev-mypy"
Requires-Dist: types-toml==0.10.8.20240310; extra == "dev-mypy"
Requires-Dist: types-Markdown==3.10.0.20251106; extra == "dev-mypy"
Requires-Dist: frequenz-lib-notebooks[dev-mkdocs,dev-noxfile,dev-pytest]; extra == "dev-mypy"
Provides-Extra: dev-noxfile
Requires-Dist: nox==2025.11.12; extra == "dev-noxfile"
Requires-Dist: frequenz-repo-config[lib]==0.13.8; extra == "dev-noxfile"
Provides-Extra: dev-pylint
Requires-Dist: frequenz-lib-notebooks[dev-mkdocs,dev-noxfile,dev-pytest]; extra == "dev-pylint"
Provides-Extra: dev-pytest
Requires-Dist: pytest==9.0.2; extra == "dev-pytest"
Requires-Dist: pylint==4.0.4; extra == "dev-pytest"
Requires-Dist: frequenz-repo-config[extra-lint-examples]==0.13.8; extra == "dev-pytest"
Requires-Dist: pytest-mock==3.15.1; extra == "dev-pytest"
Requires-Dist: pytest-asyncio==1.3.0; extra == "dev-pytest"
Requires-Dist: async-solipsism==0.9; extra == "dev-pytest"
Provides-Extra: dev
Requires-Dist: frequenz-lib-notebooks[dev-flake8,dev-formatting,dev-mkdocs,dev-mypy,dev-noxfile,dev-pylint,dev-pytest]; extra == "dev"
Dynamic: license-file
